Workbook

Sheet Conceptos técnicos
B2: PALABRA | D2: CONCEPTO TÉCNICO | G2: ORGANIZACIÓN DE LIBROS
B3: HTML | D3: El Lenguaje de Marcado de Hipertexto (HTML) es el código que se utiliza para estructurar y desplegar una página web y sus contenidos. Por ejemplo, sus contenidos podrían ser párrafos, una lista con viñetas, o imágenes y tablas de datos. | G3: BACKEND | H3: GENERALES | I3: FUNCIONALES | J3: Funcionales generales BE | N3: ESTADISTICAS
B4: CSS | D4: Hojas de Estilo en Cascada (del inglés Cascading Style Sheets) o CSS es el lenguaje de estilos utilizado para describir la presentación de documentos HTML o XML (en-US) (incluyendo varios lenguajes basados en XML como SVG, MathML o XHTML). | I4: NO FUNCIONALES | J4: No funcionales generales BE | M4: Requerimientos | N4: Funcionales | O4: =COUNT(#REF!,#REF!,#REF!,'Funcionales PRODUCTOS E INVENTA'!B12:D150,'Funcionales Carrito BE'!B12:D150,#REF!,#REF!,#REF!,#REF!,#REF!,#REF!,'[1]Funcionales Usuarios'!B12:D150,#REF!,'[2]Funcionales Autenticación BE'!B12:D150,#REF!,#REF!,#REF!,'RF PANEL USER'!B12:D150,'Funcionales generales FE'!B12:D150,#REF!,#REF!,#REF!,'[3]Funcionales Perfil usuario FE'!B12:D150,#REF!,) -> 273
B5: JavaScript | D5: JavaScript es un lenguaje de programación o de secuencias de comandos que te permite implementar funciones complejas en páginas web, cada vez que una página web hace algo más que sentarse allí y mostrar información estática para que la veas, muestra oportunas actualizaciones de contenido, mapas interactivos, animación de Gráficos 2D/3D, desplazamiento de máquinas reproductoras de vídeo, etc., puedes apostar que probablemente JavaScript está involucrado. | H5: HOME | I5: FUNCIONALES | J5: Funcionales Home BE | N5: No Funcionales | O5: =COUNT('No funcionales generales BE'!B12:D150,#REF!,#REF!,#REF!,#REF!,#REF!,#REF!,#REF!,#REF!,#REF!,#REF!,'[4]No funcionales Usuarios'!B12:D150,#REF!,#REF!,'[5]No funcionales Pasarela de pago'!B12:D150,'[6]No funcionales Notificaciones B'!B12:D150,#REF!,#REF!,'No funcionales generales FE'!B12:D150,#REF!,#REF!,#REF!,#REF!,#REF!,) -> 126
B6: VISTA | D6: En el desarrollo web, una vista puede ser una página web, pero también puede ser cualquier tipo de componente de la interfaz de usuario, como un encabezado, un pie de página, un formulario, etc. | I6: NO FUNCIONALES | J6: No funcionales Home BE | N6: TOTALES | O6: =COUNT(#REF!,'No funcionales generales BE'!B12:D150,#REF!,#REF!,#REF!,#REF!,'Funcionales PRODUCTOS E INVENTA'!B12:D150,#REF!,'Funcionales Carrito BE'!B12:D150,#REF!,#REF!,#REF!,#REF!,#REF!,#REF!,#REF!,#REF!,#REF!,#REF!,#REF!,#REF!,#REF!,'[1]Funcionales Usuarios'!B12:D150,'[4]No funcionales Usuarios'!B12:D150,#REF!,#REF!,'[2]Funcionales Autenticación BE'!B12:D150,#REF!,#REF!,'[5]No funcionales Pasarela de pago'!B12:D150,#REF!,'[6]No funcionales Notificaciones B'!B12:D150,'[7]Funcionales generales '!B12:D150,#REF!,'RF PANEL USER'!B12:D150,#REF!,'[8]Funcionales generales FE'!B12:D150,'No funcionales generales FE'!B12:D150,#REF!,#REF!,#REF!,#REF!,#REF!,#REF!,'[3]Funcionales Perfil usuario FE'!B12:D150,#REF!,#REF!,#REF!,) -> 298
B7: React | D7: Es una biblioteca Javascript de código abierto diseñada para crear interfaces de usuario con el objetivo de facilitar el desarrollo de aplicaciones en una sola página. | H7: SHOP | I7: FUNCIONALES | J7: Funcionales Shop BE | N7: Cumplidos | O7: =COUNTIF('No funcionales generales BE'!F12:F144,"x")+COUNTIF(#REF!,"x")+COUNTIF(#REF!,"x")+COUNTIF(#REF!,"x")+COUNTIF(#REF!,"x")+COUNTIF('RF PANEL USER'!F12:F99,"x")+COUNTIF(#REF!,"x")+COUNTIF(#REF!,"x")+COUNTIF(#REF!,"x")+COUNTIF(#REF!,"x")+COUNTIF('Funcionales PRODUCTOS E INVENTA'!F12:F100,"x")+COUNTIF(#REF!,"x")+COUNTIF('Funcionales Carrito BE'!F12:F100,"x")+COUNTIF(#REF!,"x")+COUNTIF(#REF!,"x")+COUNTIF(#REF!,"x")+COUNTIF(#REF!,"x")+COUNTIF(#REF!,"x")+COUNTIF(#REF!,"x")+COUNTIF(#REF!,"x")+COUNTIF(#REF!,"x")+COUNTIF(#REF!,"x")+COUNTIF(#REF!,"x")+COUNTIF(#REF!,"x")+COUNTIF(#REF!,"x")+COUNTIF(#REF!,"x")+COUNTIF('RF CLIENTES Y USUARIOS'!F12:F100,"x")+COUNTIF(#REF!,"x")+COUNTIF(#REF!,"x")+COUNTIF(#REF!,"x")+COUNTIF(#REF!,"x")+COUNTIF(#REF!,"x")+COUNTIF(#REF!,"x") -> #REF!
B8: TypeScript | D8: Es un lenguaje de programación de código abierto, creado por Microsoft, que se basa en JavaScript y añade tipos estáticos y otras características para mejorar la seguridad y la escalabilidad en el desarrollo web y de aplicaciones. | I8: NO FUNCIONALES | J8: No funcionales Shop BE | N8: No cumplidos | O8: =O6-O7 -> #REF!
B9: Nextjs | D9: Es un framework JavaScript ligero y de código abierto creado sobre React, que permite desarrollar aplicaciones y sitios web muy rápidos y fáciles de usar. | H9: PRODUCTO | I9: FUNCIONALES | J9: Funcionales Producto BE | N9: Porcentaje de cumplimiento | O9: =O7/O6 -> #REF!
B10: Python | D10: Python es un lenguaje de programación potente y fácil de aprender. Tiene estructuras de datos de alto nivel eficientes y un simple pero efectivo sistema de programación orientado a objetos. | I10: NO FUNCIONALES | J10: No funcionales Producto BE
B11: FastAPI | D11: FastAPI es un framework web moderno, rápido (de alto rendimiento), para construir APIs con Python basado en las anotaciones de tipos estándar de Python. | H11: CARRITO | I11: FUNCIONALES | J11: Funcionales Carrito BE
B12: PostgreSQL | D12: Sistema de gestión de bases de datos relacionales de código abierto | I12: NO FUNCIONALES | J12: No funcionales Carrito BE
B13: Tailwind CSS | D13: Framework de CSS utilitario para diseño rápido y responsivo | H13: CHECKOUT | I13: FUNCIONALES | J13: Funcionales Checkout BE
B14: JWT | D14: JSON Web Token para autenticación y autorización segura | I14: NO FUNCIONALES | J14: No funcionales Checkout BE
B15: Pydantic | D15: Biblioteca Python para validación de datos usando anotaciones de tipos | H15: ORDENES | I15: FUNCIONALES | J15: Funcionales Ordenes BE
B16: API REST | D16: Arquitectura para servicios web que utiliza métodos HTTP estándar | I16: NO FUNCIONALES | J16: No funcionales Ordenes BE
B17: Middleware | D17: Software que actúa como puente entre diferentes aplicaciones o servicios | H17: FAVORITOS | I17: FUNCIONALES | J17: Funcionales Favoritos BE
B18: CORS | D18: Cross-Origin Resource Sharing para permitir solicitudes entre dominios | I18: NO FUNCIONALES | J18: No funcionales Favoritos BE
B19: Shadcn/ui | D19: Biblioteca de componentes UI reutilizables para React | H19: DASHBOARD | I19: FUNCIONALES | J19: Funcionales Dashboard BE
B20: Transacciones ACID | D20: Transacciones ACID son un conjunto de reglas que garantizan que una operación en una base de datos se ejecute de forma segura y confiable. Significa que la transacción debe hacerse completamente o no hacerse (atómica), debe mantener la integridad de los datos (consistente), no debe verse afectada por otras transacciones al mismo tiempo (aislada) y sus resultados deben mantenerse incluso si ocurre un fallo (duradera). | I20: NO FUNCIONALES | J20: No funcionaes Dashboard BE
B21: CRUD | D21: CRUD es un conjunto de operaciones básicas que se pueden hacer con los datos: crear, leer, actualizar y eliminar información. | H21: GESTION PRODUCTOS | I21: FUNCIONALES | J21: Funcionales productos BE
B22: Docker | I22: NO FUNCIONALES | J22: No funcionales Productos BE
B23: Load balancing | H23: CATEGORIAS | I23: FUNCIONALES | J23: Funcionales Categorias BE
B24: Swagger | I24: NO FUNCIONALES | J24: No funcionales Categorias BE
B25: OpenAPI | H25: USUARIOS | I25: FUNCIONALES | J25: Funcionales Usuarios
B26: HTTP | I26: NO FUNCIONALES | J26: No funcionales Usuarios
B27: HTTPS | H27: DESCUENTOS | I27: FUNCIONALES | J27: Funcionales Descuentos BE
B28: Bcrypt | I28: NO FUNCIONALES | J28: No funcionales Descuentos BE
B29: DDoS | H29: AUTENTICACION | I29: FUNCIONALES | J29: Funcionales Autenticación BE
B30: Cookies | I30: NO FUNCIONALES | J30: No funcionales Autenticacion BE
B31: Normativas de datos GDPR | H31: PASARELA DE PAGO | I31: FUNCIONALES | J31: Funcionales Pasarela pagos BE
B32: Normativas de datos GDPR | I32: NO FUNCIONALES | J32: No funcionales Pasarela de pago
B33: Lazy Loading | H33: NOTIFICACIONES | I33: FUNCIONALES | J33: Funcionales Notificaciones BE
B34: CSRF | I34: NO FUNCIONALES | J34: No funcionales Notificaciones BE
B35: JSON | G35: DB | H35: GENERALES | I35: FUNCIONALES | J35: Funcionales generales DB
B36: XML | I36: NO FUNCIONALES | J36: No funcionales generales DB
B37: UTF-8 | G37: SYNKRO (Modelo de negocio) | H37: GENERALES | I37: FUNCIONALES | J37: Funcionales synkro
B38: Slider | I38: NO FUNCIONALES | J38: No funcionales Synkro
B39: Sidebar | G39: FRONTEND | H39: GENERALES | I39: FUNCIONAL | J39: Funcionales generales FE
B40: Newsletter | I40: NO FUNCIONAL | J40: No funcionales generales FE
B41: Notifiaciones TOAST | H41: HOME | I41: FUNCIONAL | J41: Funcionales Home FE
I42: NO FUNCIONAL | J42: No funcionales Home FE
H43: PRODUCTO | I43: FUNCIONAL | J43: Funcionales Producto FE
I44: NO FUNCIONAL | J44: No funcionales Producto FE
H45: CARRITO | I45: FUNCIONAL | J45: Funcionales Carrito FE
I46: NO FUNCIONAL | J46: No funcionales Carrito FE
H47: PERFIL DE USUARIO | I47: FUNCIONAL | J47: Funcionales Perfil usuario FE
I48: NO FUNCIONAL | J48: No funcionales user profile FE
H49: DASHBOARD | I49: FUNCIONAL | J49: Funcionales Dashboard FE
I50: NO FUNCIONAL | J50: No funcionales Dashboard FE

Sheet No funcionales generales BE
B2: LISTADO DE REQUERIMIENTOS DE RDWATCH | K2: ESTADISTICAS
K3: Requirimientos | L3: =COUNT(B12:D94) -> 60
B4: SI | C4: Marque con una equis (X) si el sistema cumple con la función descrita | K4: Cumplidos | L4: =COUNTIF(F12:F94,"X") -> 38
B5: NO | C5: Marque con una equis (X) si el sistema no cumple con la función descrita
B6: ADI | C6: Marque con una equis (X) si el sistema debe adicionar la función descrita | I6: =COUNTIF('No funcionales generales BE'!F12:F144,"x")+COUNTIF(#REF!,"x")+COUNTIF(#REF!,"x")+COUNTIF(#REF!,"x")+COUNTIF(#REF!,"x")+COUNTIF('RF PANEL USER'!F12:F99,"x")+COUNTIF(#REF!,"x")+COUNTIF(#REF!,"x")+COUNTIF(#REF!,"x")+COUNTIF(#REF!,"x")+COUNTIF('Funcionales PRODUCTOS E INVENTA'!F12:F100,"x")+COUNTIF(#REF!,"x")+COUNTIF('Funcionales Carrito BE'!F12:F100,"x")+COUNTIF(#REF!,"x")+COUNTIF(#REF!,"x")+COUNTIF(#REF!,"x")+COUNTIF(#REF!,"x")+COUNTIF(#REF!,"x")+COUNTIF(#REF!,"x")+COUNTIF(#REF!,"x")+COUNTIF(#REF!,"x")+COUNTIF(#REF!,"x")+COUNTIF(#REF!,"x")+COUNTIF(#REF!,"x")+COUNTIF(#REF!,"x")+COUNTIF(#REF!,"x")+COUNTIF('RF CLIENTES Y USUARIOS'!F12:F100,"x")+COUNTIF(#REF!,"x")+COUNTIF(#REF!,"x")+COUNTIF(#REF!,"x")+COUNTIF(#REF!,"x")+COUNTIF(#REF!,"x")+COUNTIF(#REF!,"x") -> #REF! | K6: Porcentaje | L6: =_xludf.PERCENTOF(L4,L3) -> #NAME?
B7: Observaciones: | D7: Espacio para complementar respuestas
F9: Nivel de cumplimiento | I9: OBSERVACIONES
B10: REQUISITOS NO FUNCIONALES BACKEND | F10: SI | G10: NO | H10: ADI
B12: 1 | C12: La base de datos del sistema debe permitir integridad relacional | F12: X
B13: 2 | C13: La base de datos del sistema debe estar normalizada teniendo en cuenta las 13 leyes de Codd | F13: X
B14: 3 | C14: Las consultas SELECT en tab_Productos con filtros por categoría, marca y subcategoría deben ejecutarse en menos de 200ms para hasta 10,000 productos | H14: X
B15: 4 | C15: La búsqueda por nom_producto usando LIKE o full-text search debe retornar resultados en menos de 300ms | F15: X
B16: 5 | C16: La recuperación completa de productos del carrito (tab_Carrito_Detalle con JOINs) debe ejecutarse en menos de 150ms | H16: X
B17: 6 | C17: La inserción de una orden completa en tab_Orden y tab_Detalle_Orden debe completarse en menos de 1 segundo | F17: X
B18: 7 | C18: La actualización de stock en tab_Productos y registro en tab_Recepciones_Proveedor debe ser atómica y completarse en menos de 100ms | F18: X
B19: 8 | C19: La consulta de promociones activas en tab_Promociones debe ejecutarse en menos de 50ms | H19: X
B20: 9 | C20: La consulta de descuentos aplicables en tab_Productos_Promociones con todas las validaciones de fechas y condiciones debe ejecutarse en menos de 100ms | F20: X
B21: 10 | C21: La consulta de historial de órdenes en tab_Orden por usuario debe retornar resultados en menos de 300ms para hasta 1000 órdenes | F21: X
B22: 11 | C22: La consulta en tab_Facturas y tab_Detalle_Factura debe generar reportes en menos de 2 segundos | F22: X
B23: 12 | C23: La consulta de opiniones de productos en tab_Opiniones debe ejecutarse en menos de 100ms | F23: X
B24: 13 | C24: El sistema debe soportar 1,000 usuarios simultáneos navegando el catálogo sin degradación de performance | H24: X
B25: 14 | C25: tab_Productos debe soportar hasta 10 millones de registros con estado = TRUE manteniendo performance | F25: X
B26: 15 | C26: tab_Orden debe poder manejar hasta 1 millón registros con particionamiento por fecha | H26: X
B27: 16 | C27: tab_Recepciones_Proveedor debe escalar hasta 50 millones de registros con archivado automático | H27: X
B28: 17 | C28: El sistema debe procesar mínimo 500 transacciones por segundo en tab_Orden durante picos de demanda | H28: X
B29: 18 | C29: El sistema debe mantener 99.9% de uptime, con máximo 8.77 horas de downtime por año | F29: X
B30: 19 | C30: En caso de fallo de base de datos, el sistema debe recuperarse en menos de 15 minutos | H30: X
B31: 20 | C31: En caso de fallo, la pérdida máxima de datos debe ser de 1 hora (RPO) | F31: X
B32: 21 | C32: tab_Usuarios, tab_Orden, tab_Productos, tab_Direcciones_Envio deben tener backup cada 24 horas | F32: X
B33: 22 | C33: Las transacciones en tab_Orden, tab_Detalle_Orden y tab_Orden_Servicios deben ser completamente ACID | F33: X
B34: 23 | C34: Las actualizaciones de stock en tab_Productos deben ser consistentes con tab_Recepciones_Proveedor | F34: X
B35: 24 | C35: Los datos de auditoría (usr_insert, fec_insert, etc.) deben ser consistentes en todas las tablas | H35: X
B36: 25 | C36: Todas las FK en el sistema deben ser validadas antes de inserción, especialmente las compuestas en tab_Subcategorias y tab_Productos | F36: X
B37: 26 | C37: Todas las transacciones deben poder hacer rollback completo en caso de error | F37: X
B38: 27 | C38: Los bloqueos en tab_Productos durante actualizaciones de inventario no deben exceder 100ms | F38: X
B39: 28 | C39: Los datos sensibles en tab_Usuarios deben estar encriptados con bcrypt o algoritmo equivalente | F39: X
B40: 29 | C40: correo_usuario y num_telefono_usuario en tab_Usuarios deben estar protegidos contra acceso no autorizado | F40: X
B41: 30 | C41: Todos los cambios en tab_Usuarios, tab_Orden, tab_Productos deben quedar registrados con usr_update y fec_update
B42: 31 | C42: El acceso a tablas debe estar controlado por roles definidos en el sistema de gestión de base de datos
B43: 32 | C43: Todas las consultas a tab_Productos y tab_Usuarios deben usar prepared statements | F43: X
B44: 33 | C44: Los datos eliminados deben quedar registrados en campos de auditoría (usr_delete, fec_delete) para auditoría | H44: X
B45: 34 | C45: Todos los campos de entrada en tab_Usuarios deben ser validados contra patrones maliciosos | F45: X
B46: 35 | C46: Las sesiones inactivas en tab_Carrito deben expirar después de 30 minutos | F46: X
B47: 36 | C47: Los intentos fallidos de acceso deben ser limitados para prevenir ataques de fuerza bruta
B48: 37 | C48: Todas las tablas deben tener comentarios explicativos de su propósito y relaciones
B49: 38 | C49: Todos los cambios en el esquema deben estar versionados y documentados | F49: X
B50: 39 | C50: Todos los cambios en tab_Productos y tablas relacionadas deben tener scripts de migración | F50: X
B51: 40 | C51: Los cambios de esquema deben poder revertirse sin pérdida de datos | F51: X
B52: 41 | C52: Las consultas lentas en tab_Productos, tab_Orden y tab_Facturas deben ser detectadas automáticamente | F52: X
B53: 42 | C53: El sistema debe generar alertas automáticas cuando tab_Recepciones_Proveedor alcance 80% del espacio asignado
B54: 43 | C54: Los registros antiguos en tab_Carrito sin actividad por más de 30 días deben eliminarse automáticamente
B55: 44 | C55: Todas las consultas frecuentes en tab_Productos deben tener índices específicos (ej: idx_producto_nombre) | F55: X
B56: 45 | C56: tab_Orden debe estar particionada por fecha para optimizar consultas históricas | H56: X
B57: 46 | C57: Los registros en tab_Recepciones_Proveedor mayores a 2 años deben archivarse automáticamente | F57: X
B58: 47 | C58: tab_Usuarios debe soportar hasta 100000 de usuarios registrados sin degradación | F58: X
B59: 48 | C59: tab_Productos debe manejar hasta 10 millones de productos con performance óptima
B60: 49 | C60: tab_Orden debe procesar hasta 50,000 órdenes diarias sin problemas de performance
B61: 50 | C61: url_imagen en tab_Productos debe soportar URLs de hasta 500 caracteres
B62: 51 | C62: tab_Opiniones debe retener historial completo por 5 años
B63: 52 | C63: Los datos históricos en tab_Orden mayores a 1 año deben comprimirse automáticamente | F63: X
B64: 53 | C64: El sistema debe permitir realizar análisis jerárquico (drill down y drill up) en diferentes módulos | F64: X
B65: 54 | C65: El sistema debe soportar concurrencia multiusuario sin pérdida o colisión de datos | F65: X
B66: 55 | C66: El sistema debe emplear carga de datos asíncrona para mejorar la experiencia del usuario y reducir los tiempos de espera | F66: X
B67: 56 | C67: Las consultas SQL deben estar optimizadas mediante índices, paginación y mecanismos de caché donde sea aplicable | F67: X
B68: 57 | C68: Los módulos deben desarrollarse de forma desacoplada y modular, facilitando el mantenimiento y escalabilidad del sistema | H68: X
B69: 58 | C69: El sistema debe soportar procedimientos almacenados, triggers y vistas, ejecutados en el servidor para mejorar el rendimiento y facilitar la reutilización | F69: X
B70: 59 | C70: El código fuente debe seguir buenas prácticas de desarrollo | F70: X
B71: 60 | C71: El sistema debe ser compatible con los principales navegadores actuales (Chrome, Firefox, Edge, Safari) y sus dos últimas versiones | F71: X

Sheet Funcionales generales FE
B2: LISTADO DE REQUERIMIENTOS DE RDWATCH | K2: ESTADISTICAS
K3: Requirimientos | L3: =COUNT(B12:C111) -> 100
B4: SI | C4: Marque con una equis (X) si el sistema cumple con la función descrita | K4: Cumplidos | L4: =COUNTIF(F12:F111,"X") -> 100
B5: NO | C5: Marque con una equis (X) si el sistema no cumple con la función descrita
B6: ADI | C6: Marque con una equis (X) si el sistema debe adicionar la función descrita | K6: Porcentaje | L6: =L3/L4 -> 1
B7: Observaciones: | D7: Espacio para complementar respuestas
F9: Nivel de cumplimiento | I9: OBSERVACIONES
B10: REQUISITOS FUNCIONALES GENERALES FRONT-END | F10: SI | G10: NO | H10: ADI
B12: 1 | C12: El sistema debe mostrar un header fijo que permanece visible al hacer scroll | F12: X
B13: 2 | C13: El header debe cambiar de transparente a sólido (con sombra) al hacer scroll más de 50px | F13: X
B14: 3 | C14: El logo debe redirigir al inicio del sitio | F14: X
B15: 4 | C15: El menú de navegación debe incluir enlaces a: Servicios, Sobre Nosotros, Reseñas, Galería, Contacto | F15: X
B16: 5 | C16: Los enlaces de navegación deben tener efecto underline animado al pasar el mouse | F16: X
B17: 6 | C17: El sistema debe implementar smooth scrolling para enlaces internos | F17: X
B18: 7 | C18: El header debe incluir botones de acción: "Mi Cuenta" y "Contacto" | F18: X
B19: 8 | C19: El sistema debe mostrar un preloader animado al cargar la página | F19: X
B20: 9 | C20: El preloader debe simular un reloj con manecillas en movimiento | F20: X
B21: 10 | C21: El preloader debe desaparecer después de 1.5 segundos con efecto fade-out | F21: X
B22: 11 | C22: El preloader debe ocupar toda la pantalla con fondo oscuro | F22: X
B23: 12 | C23: El hero debe mostrar título principal "Relojería Durán" | F23: X
... B111: 100 | C111: El botón debe hacer scroll suave hacia el inicio al hacer clic | F111: X

Sheet RF Landing Comercio
B2: LISTADO DE REQUERIMIENTOS DE RDWATCH | K2: ESTADISTICAS
K3: Requirimientos | L3: =COUNT(B12:D108) -> 97
B4: SI | C4: Marque con una equis (X) si el sistema cumple con la función descrita | K4: Cumplidos | L4: =COUNTIF(F12:F108,"X") -> 97
B5: NO | C5: Marque con una equis (X) si el sistema no cumple con la función descrita
B6: ADI | C6: Marque con una equis (X) si el sistema debe adicionar la función descrita | K6: Porcentaje | L6: =L3/L4 -> 1
B7: Observaciones: | D7: Espacio para complementar respuestas
F9: Nivel de cumplimiento | I9: OBSERVACIONES
B10: REQUISITOS FUNCIONALES COMERCIO | F10: SI | G10: NO | H10: ADI
B12: 1 | C12: La página debe mostrar un banner hero con título "Nuestra Colección" | F12: X
B13: 2 | C13: El banner debe incluir subtítulo descriptivo | F13: X
B14: 3 | C14: El filtro activo debe estar resaltado | F14: X
B15: 4 | C15: El sistema debe incluir selector de marcas: Todas, Rolex, Omega, Citizen, Otras | F15: X
B16: 5 | C16: Los enlaces de navegación deben tener efecto underline animado al pasar el mouse | F16: X
B17: 6 | C17: El sistema debe implementar smooth scrolling para enlaces internos | F17: X
B18: 7 | C18: El header debe incluir botones de acción: "Mi Cuenta" y "Contacto" | F18: X
B19: 8 | C19: El sistema debe mostrar un preloader animado al cargar la página | F19: X
B20: 9 | C20: El preloader debe simular un reloj con manecillas en movimiento | F20: X
B21: 10 | C21: El preloader debe desaparecer después de 1.5 segundos con efecto fade-out | F21: X
B22: 11 | C22: El preloader debe ocupar toda la pantalla con fondo oscuro | F22: X
B23: 12 | C23: El hero debe mostrar título principal "Relojería Durán" | F23: X
... B108: 97 | C108: La funcionalidad debe aplicarse a todos los campos de contraseña | F108: X

Sheet No funcionales generales FE
B2: LISTADO DE REQUERIMIENTOS DE RDWATCH | K2: ESTADISTICAS
K3: Requirimientos | L3: =COUNT(B12:D99) -> 65
B4: SI | C4: Marque con una equis (X) si el sistema cumple con la función descrita | K4: Cumplidos | L4: =COUNTIF(F12:F99,"X") -> 1
B5: NO | C5: Marque con una equis (X) si el sistema no cumple con la función descrita
B6: ADI | C6: Marque con una equis (X) si el sistema debe adicionar la función descrita | K6: Porcentaje | L6: =L3/L4 -> 65
B7: Observaciones: | D7: Espacio para complementar respuestas
F9: Nivel de cumplimiento | I9: OBSERVACIONES
B10: REQUISITOS FUNCIONALES GENERALES FRONT-END | F10: SI | G10: NO | H10: ADI
B12: 1 | C12: La página debe cargar completamente en menos de 3 segundos | F12: x
B13: 2 | C13: El preloader debe mostrarse durante la carga inicial | H13: X
B14: 3 | C14: Las imágenes deben usar lazy-loading | H14: X
B15: 4 | C15: Los recursos estáticos deben cargarse desde CDN (FontAwesome, Google Fonts) | H15: X
B16: 5 | C16: Las imágenes deben estar optimizadas (comprimidas) | H16: X
B17: 6 | C17: Las transiciones deben usar propiedades optimizadas (transform, opacity) | H17: X
B18: 7 | C18: Las animaciones pesadas deben pausarse cuando no están visibles | H18: X
B19: 8 | C19: El sistema debe proporcionar feedback visual para todas las acciones | H19: X
B20: 9 | C20: Los botones deben tener estados hover claramente diferenciados | H20: X
B21: 10 | C21: El cursor debe cambiar a pointer sobre elementos clicables | H21: X
B22: 11 | C22: El sistema debe usar smooth scrolling para mejorar la experiencia | H22: X
B23: 12 | C23: Los campos de formulario deben tener validación visual en tiempo real | H23: X
B24: 13 | C24: Los errores deben mostrarse claramente debajo de cada campo | H24: X
... B76: 65 | C76: Los archivos deben organizarse lógicamente: HTML, CSS, JS separados | H76: X

Sheet RF PANELADMIN
B2: LISTADO DE REQUERIMIENTOS DE RDWATCH | K2: ESTADISTICAS
K3: Requirimientos | L3: =COUNT(B12:D99) -> 83
B4: SI | C4: Marque con una equis (X) si el sistema cumple con la función descrita | K4: Cumplidos | L4: =COUNTIF(F12:F99,"X") -> 8
B5: NO | C5: Marque con una equis (X) si el sistema no cumple con la función descrita
B6: ADI | C6: Marque con una equis (X) si el sistema debe adicionar la función descrita | K6: Porcentaje | L6: =L3/L4 -> 10.375
B7: Observaciones: | D7: Espacio para complementar respuestas
F9: Nivel de cumplimiento | I9: OBSERVACIONES
B10: REQUERIMIENTOS FUNCIONALES PANEL ADMINISTRATIVO | F10: SI | G10: NO | H10: ADI
B12: 1 | C12: El sistema debe permitir autenticar usuarios administrativos con credenciales únicas | F12: x
B13: 2 | C13: El sistema debe restringir el acceso al panel solo a usuarios autenticados | H13: X
B14: 3 | C14: El sistema debe registrar intentos fallidos de autenticación | H14: X
B15: 4 | C15: El sistema debe cerrar sesión automáticamente por inactividad prolongada | H15: X
B16: 5 | C16: El sistema debe permitir recuperación de contraseña mediante correo electrónico | H16: X
B17: 6 | C17: El sistema debe implementar autenticación de dos factores (2FA) | H17: X
B18: 7 | C18: El sistema debe restringir acceso a módulos según el rol del usuario | H18: X
B19: 8 | C19: El sistema debe permitir personalizar menús según permisos del usuario | H19: X
B20: 9 | C20: El sistema debe mostrar el total de órdenes | H20: X
B21: 10 | C21: El sistema debe mostrar los ingresos totales | H21: X
B22: 11 | C22: El sistema debe mostrar el total de clientes registrados | H22: X
B23: 12 | C23: El sistema debe mostrar el total de productos en inventario | H23: X
B24: 13 | C24: El sistema debe mostrar el total de visitantes del sitio | H24: X
... B30: 19 | C30: El dashboard debe mostrar métricas clave con iconos y colores | H30: X
B31: 20 | C31: El sistema debe permitir aplicar filtros por rango de fechas en estadísticas | F31: x
B32: 21 | C32: El sistema debe permitir comparar períodos (mes actual vs anterior) | H32: X
B33: 22 | C33: El sistema debe consolidar información analítica de ventas, productos y clientes | H33: X
B34: 23 | C34: El sistema debe permitir crear productos | H34: X
B35: 24 | C35: El sistema debe permitir editar productos | H35: X
B36: 25 | C36: El sistema debe permitir eliminar productos con confirmación | H36: X
B37: 26 | C37: El sistema debe permitir listar todos los productos | F37: x
B38: 27 | C38: El sistema debe permitir asignar categorías y subcategorías a productos | H38: X
B39: 28 | C39: El sistema debe permitir asignar marca al producto | H39: X
B40: 29 | C40: El sistema debe permitir asignar múltiples imágenes a un producto | H40: X
B41: 30 | C41: El sistema debe permitir configurar variantes de producto (talla, color, presentación) | H41: X
B42: 31 | C42: El sistema debe permitir clasificar productos como nuevos lanzamientos | H42: X
B43: 32 | C43: El sistema debe permitir activar o desactivar productos | H43: X
B44: 33 | C44: El sistema debe mostrar el stock disponible por producto en tiempo real | H44: X
B45: 34 | C45: El sistema debe permitir configurar stock mínimo y máximo por producto | F45: x
B46: 35 | C46: El sistema debe emitir alertas al alcanzar niveles mínimos de stock | H46: X
B47: 36 | C47: El sistema debe registrar movimientos de inventario asociados a ventas | H47: X
B48: 37 | C48: El sistema debe registrar movimientos de inventario asociados a devoluciones | H48: X
B49: 38 | C49: El sistema debe registrar ajustes manuales de inventario | H49: X
B50: 39 | C50: El sistema debe auditar movimientos de inventario con historial de cambios | H50: X
B51: 40 | C51: El sistema debe permitir buscar productos por nombre | H51: X
B52: 41 | C52: El sistema debe permitir filtrar productos por categoría | H52: X
B53: 42 | C53: El sistema debe permitir filtrar productos por marca | H53: X
B54: 43 | C54: El sistema debe permitir filtrar productos por estado (activo/inactivo) | H54: X
B55: 44 | C55: El sistema debe listar todos los pedidos con información básica | H55: X
B56: 45 | C56: El sistema debe mostrar el detalle completo de cada pedido | H56: X
B57: 46 | C57: El sistema debe mostrar el cliente asociado a cada pedido | H57: X
... B63: 52 | C63: El sistema debe permitir procesar devoluciones | H63: X
B64: 53 | C64: El sistema debe permitir procesar cancelaciones | F64: x
B65: 54 | C65: El sistema debe registrar el uso de cupones en pedidos | F65: x
B66: 55 | C66: El sistema debe listar todos los clientes registrados | H66: X
B67: 56 | C67: El sistema debe mostrar información de contacto de clientes | H67: X
B68: 57 | C68: El sistema debe mostrar el historial de compras por cliente | H68: X
B69: 58 | C69: El sistema debe filtrar clientes por ingresos y total de órdenes | H69: X
B70: 59 | C70: El sistema debe mostrar el historial de actividad por cliente | H70: X
B71: 60 | C71: El sistema debe permitir editar información de clientes | H71: X
B72: 61 | C72: El sistema debe permitir activar/desactivar cuentas de clientes | H72: X
B73: 62 | C73: El sistema debe permitir buscar clientes por nombre, email o teléfono | H73: X
B74: 63 | C74: El sistema debe permitir crear cupones de descuento | H74: X
B75: 64 | C75: El sistema debe permitir editar cupones de descuento | H75: X
B76: 65 | C76: El sistema debe permitir eliminar cupones de descuento | H76: X
B77: 66 | C77: El sistema debe permitir definir condiciones de aplicación de cupones | H77: X
... B83: 72 | C83: El sistema debe generar reporte de ventas por período | H83: X
B84: 73 | C84: El sistema debe generar reporte de productos más vendidos | F84: x
B85: 74 | C85: El sistema debe generar reporte de inventario actual | H85: X
B86: 75 | C86: El sistema debe permitir configurar datos de la tienda (nombre, moneda) | H86: X
B87: 76 | C87: El sistema debe permitir cambiar credenciales de administrador | H87: X
B88: 77 | C88: El sistema debe permitir configurar políticas de envío | H88: X
B89: 78 | C89: El sistema debe permitir configurar políticas de devolución | H89: X
B90: 79 | C90: El sistema debe permitir gestionar contenido legal (términos, privacidad) | F90: x
B91: 80 | C91: El sistema debe permitir configurar métodos de pago aceptados | H91: X
B92: 81 | C92: El sistema debe permitir configurar pasarelas de pago | H92: X
B93: 82 | C93: El sistema debe permitir asignar múltiples imágenes a un producto | H93: X
B94: 83 | C94: El sistema debe permitir configurar notificaciones automáticas | H94: X

Sheet RF PANEL USER
B2: LISTADO DE REQUERIMIENTOS DE RDWATCH | K2: ESTADISTICAS
K3: Requirimientos | L3: =COUNT(B12:D99) -> 88
B4: SI | C4: Marque con una equis (X) si el sistema cumple con la función descrita | K4: Cumplidos | L4: =COUNTIF(F12:F99,"X") -> 8
B5: NO | C5: Marque con una equis (X) si el sistema no cumple con la función descrita
B6: ADI | C6: Marque con una equis (X) si el sistema debe adicionar la función descrita | K6: Porcentaje | L6: =L3/L4 -> 11
B7: Observaciones: | D7: Espacio para complementar respuestas
F9: Nivel de cumplimiento | I9: OBSERVACIONES
B10: REQUERIMIENTOS FUNCIONALES PANEL USUARIO | F10: SI | G10: NO | H10: ADI
B12: 1 | C12: El sistema debe mostrar información básica del usuario (nombre, email, teléfono) en la cabecera de su perfil | F12: x
B13: 2 | C13: El sistema debe permitir visualizar información completa del cliente | H13: X
B14: 3 | C14: El sistema debe permitir editar información personal del cliente | H14: X
B15: 4 | C15: El sistema debe validar el formato del correo electrónico antes de guardar | H15: X
B16: 5 | C16: El sistema debe validar el número de teléfono en formato internacional | H16: X
B17: 6 | C17: El sistema debe validar que el correo sea único antes de actualizar | H17: X
B18: 7 | C18: El sistema debe mostrar confirmación tras actualizar el perfil exitosamente | H18: X
B19: 8 | C19: El sistema debe permitir al cliente eliminar su cuenta bajo solicitud (REQ- | H19: X
B20: 9 | C20: El sistema debe mostrar un avatar o foto de perfil del usuario | H20: X
B21: 10 | C21: El sistema debe permitir cambiar la foto de perfil | H21: X
B22: 11 | C22: El sistema debe permitir cambiar la contraseña | H22: X
B23: 12 | C23: El sistema debe validar fortaleza de contraseña al cambiarla | H23: X
B24: 13 | C24: El sistema debe solicitar contraseña actual antes de cambiarla | H24: X
... B30: 19 | C30: El sistema debe permitir agregar etiquetas a direcciones (Casa, Trabajo, Otro) | H30: X
B31: 20 | C31: El sistema debe validar campos obligatorios de dirección | F31: x
B32: 21 | C32: El sistema debe autocompletar dirección si el usuario está registrado | H32: X
B33: 22 | C33: El sistema debe validar formato de código postal | H33: X
B34: 23 | C34: El sistema debe mostrar confirmación al guardar/eliminar direcciones | H34: X
B35: 24 | C35: El sistema debe mostrar el historial de compras del cliente (REQ-004) | H35: X
B36: 25 | C36: El sistema debe permitir realizar seguimiento en tiempo real del estado de pedidos | H36: X
B37: 26 | C37: El sistema debe mostrar detalles completos de cada pedido | F37: x
B38: 27 | C38: El sistema debe mostrar el estado actual de cada pedido | H38: X
B39: 28 | C39: El sistema debe mostrar la fecha de cada pedido | H39: X
B40: 29 | C40: El sistema debe mostrar el total pagado por pedido | H40: X
B41: 30 | C41: El sistema debe permitir filtrar pedidos por estado | H41: X
B42: 31 | C42: El sistema debe permitir filtrar pedidos por rango de fechas | H42: X
B43: 32 | C43: El sistema debe mostrar el tiempo estimado de entrega (REQ-057) | H43: X
B44: 33 | C44: El sistema debe permitir ver factura de cada pedido | H44: X
B45: 34 | C45: El sistema debe permitir descargar factura en PDF | F45: x
B46: 35 | C46: El sistema debe permitir solicitar cancelación de pedido | H46: X
B47: 36 | C47: El sistema debe permitir solicitar devolución de pedido | H47: X
B48: 37 | C48: El sistema debe permitir rastrear envío con número de guía | H48: X
B49: 38 | C49: El sistema debe notificar al usuario sobre cambios en el estado del pedido | H49: X
B50: 39 | C50: El sistema debe permitir reordenar productos de pedidos anteriores | H50: X
B51: 40 | C51: El sistema debe permitir gestionar métodos de pago guardados de forma segura | H51: X
B52: 41 | C52: El sistema debe permitir agregar nuevas tarjetas de crédito/débito | H52: X
B53: 42 | C53: El sistema debe permitir eliminar tarjetas guardadas | H53: X
B54: 43 | C54: El sistema debe mostrar solo los últimos 4 dígitos de tarjetas guardadas | H54: X
B55: 44 | C55: El sistema debe permitir marcar una tarjeta como predeterminada | H55: X
B56: 45 | C56: El sistema debe validar número de tarjeta antes de guardar | H56: X
B57: 46 | C57: El sistema debe validar fecha de expiración | H57: X
... B63: 52 | C63: El sistema debe notificar cuando un producto favorito tenga descuento | H63: X
B64: 53 | C64: El sistema debe permitir agregar productos favoritos al carrito | F64: x
B65: 54 | C65: El sistema debe mostrar disponibilidad de productos favoritos | F65: x
B66: 55 | C66: El sistema debe permitir calificar productos desde el historial de compras | H66: X
B67: 56 | C67: El sistema debe permitir crear reseñas de productos específicos | H67: X
B68: 57 | C68: El sistema debe permitir actualizar una reseña | H68: X
B69: 58 | C69: El sistema debe permitir eliminar una reseña | H69: X
B70: 59 | C70: El sistema debe mostrar todas las reseñas del usuario | H70: X
B71: 60 | C71: El sistema debe permitir adjuntar imágenes a las reseñas | H71: X
B72: 61 | C72: El sistema debe mostrar notificaciones importantes al usuario | H72: X
B73: 62 | C73: El sistema debe permitir marcar notificaciones como leídas | H73: X
B74: 63 | C74: El sistema debe permitir configurar preferencias de notificaciones | H74: X
B75: 64 | C75: El sistema debe enviar emails de confirmación de cambios importantes | H75: X
B76: 65 | C76: El sistema debe mostrar un dashboard con tarjetas informativas | H76: X
B77: 66 | C77: El sistema debe permitir navegación entre secciones desde el menú superior | H77: X
... B83: 72 | C83: El sistema debe validar campos de formularios en tiempo real | H83: X
B84: 73 | C84: El sistema debe mostrar mensajes de error específicos | F84: x
B85: 74 | C85: El sistema debe mostrar confirmaciones visuales para acciones | H85: X
B86: 75 | C86: El sistema debe mostrar estados de carga durante operaciones | H86: X
B87: 76 | C87: El sistema debe validar y sanitizar todas las entradas del usuario | H87: X
B88: 77 | C88: El sistema debe proteger contra ataques XSS y CSRF | H88: X
B89: 78 | C89: El sistema debe transmitir datos sensibles solo por HTTPS | H89: X
B90: 79 | C90: El sistema debe implementar autenticación mediante tokens JWT (REQ- | F90: x
B91: 80 | C91: El sistema debe cargar el dashboard en menos de 2 segundos | H91: X
B92: 81 | C92: El sistema debe emplear carga asíncrona para datos (REQ-124) | H92: X
B93: 82 | C93: El sistema debe implementar paginación en listas largas | H93: X
B94: 83 | C94: El panel debe ser responsive y funcionar en móviles (REQ-143) | H94: X
B95: 84 | C95: El panel debe ser compatible con navegadores principales (REQ-142)
B96: 85 | C96: El diseño debe ser coherente con el sitio principal (REQ-146)
B97: 86 | C97: El sistema debe garantizar contraste adecuado (REQ-149, REQ-157)
B98: 87 | C98: Los formularios deben tener etiquetas asociadas correctamente (REQ-159)
B99: 88 | C99: Los elementos interactivos deben tener aria-label (REQ-160)
B100: 89 | C100: El sistema debe soportar navegación por teclado

Sheet Funcionales PRODUCTOS E INVENTA
B2: LISTADO DE REQUERIMIENTOS DE RDWATCH | K2: ESTADISTICAS
K3: Requirimientos | L3: =COUNT(B12:D100) -> 41
B4: SI | C4: Marque con una equis (X) si el sistema cumple con la función descrita | K4: Cumplidos | L4: =COUNTIF(F12:F100,"X") -> 0
B5: NO | C5: Marque con una equis (X) si el sistema no cumple con la función descrita | K5: Porcentaje | L5: =_xludf.PERCENTOF(L4,L3) -> #NAME?
B6: ADI | C6: Marque con una equis (X) si el sistema debe adicionar la función descrita
B7: Observaciones: | D7: Espacio para complementar respuestas
F10: Nivel de cumplimiento | I10: Observaciones
B11: REQUERIMIENTOS FUNCIONALES PRODUCTOS E INVENTARIO | F11: SI | G11: NO | H11: ADI
B13: 1 | C13: El sistema debe mostrar un catálogo de productos con imagen, nombre y precio | H13: X
B14: 2 | C14: La página debe mostrar un banner hero con título "Nuestra Colección" | H14: X
B15: 3 | C15: El sistema debe mostrar información básica de cada producto en la tarjeta | H15: X
B16: 4 | C16: El sistema debe mostrar badge de "Nuevo" o "Oferta" en productos destacados | H16: X
B17: 5 | C17: El sistema debe permitir asociar productos relacionados o complementarios | H17: X
B18: 6 | C18: El sistema debe mostrar disponibilidad de stock en cada producto | H18: X
B19: 7 | C19: El sistema debe mostrar alerta de stock límite en productos | H19: X
B20: 8 | C20: El sistema debe mostrar calificación con estrellas de cada producto | H20: X
B21: 9 | C21: El sistema debe mostrar vista detallada al hacer clic en un producto | H21: X
B22: 10 | C22: El sistema debe mostrar múltiples imágenes del producto | H22: X
B23: 11 | C23: El sistema debe mostrar descripción completa del producto
B24: 12 | C24: El sistema debe mostrar especificaciones técnicas del producto
B25: 13 | C25: El sistema debe mostrar variantes de producto (talla, color) si aplica
B26: 14 | C26: El sistema debe permitir hacer zoom en las imágenes de producto
B27: 15 | C27: El sistema debe mostrar productos relacionados en la vista de detalle
B28: 16 | C28: El sistema debe incluir una barra de búsqueda para productos
B29: 17 | C29: El sistema debe mostrar sugerencias de búsqueda o autocompletado
B30: 18 | C30: El sistema debe manejar búsquedas sin resultados de manera informativa
B31: 19 | C31: El sistema debe permitir búsqueda por nombre de producto
B32: 20 | C32: El sistema debe permitir búsqueda por código
B33: 21 | C33: El sistema debe incluir filtros por categoría
B34: 22 | C34: El sistema debe incluir filtros por marca
... B45: 33 | C45: El sistema debe permitir ordenar por fecha de agregado (nuevos)
B46: 34 | C46: El sistema debe mostrar cada producto en una tarjeta | H46: X
B47: 35 | C47: Cada tarjeta debe incluir: imagen, categoría, marca, nombre, precio, stock, botones de acción | H47: X
B48: 36 | C48: Las tarjetas deben elevarse (translateY) al pasar el mouse+ | H48: X
B49: 37 | C49: Cada tarjeta debe incluir botón "Añadir al carrito" | H49: X
B50: 38 | C50: Cada tarjeta debe incluir botón "Ver" para detalles | H50: X
B51: 39 | C51: Los precios deben formatearse como moneda (formato USD con separadores) | H51: X
B52: 40 | C52: El sistema debe incluir controles de paginación: Anterior, Página actual, Siguiente | H52: X
B53: 41 | C53: Los botones deben estar deshabilitados cuando corresponda | H53: X

Sheet RF ORDENES Y PAGOS
B2: LISTADO DE REQUERIMIENTOS DE RDWATCH | K2: ESTADISTICAS
K3: Requirimientos | L3: =COUNT(B12:D100) -> 55
B4: SI | C4: Marque con una equis (X) si el sistema cumple con la función descrita | K4: Cumplidos | L4: =COUNTIF(F12:F100,"X") -> 0
B5: NO | C5: Marque con una equis (X) si el sistema no cumple con la función descrita | K5: Porcentaje | L5: =_xludf.PERCENTOF(L4,L3) -> #NAME?
B6: ADI | C6: Marque con una equis (X) si el sistema debe adicionar la función descrita
B7: Observaciones: | D7: Espacio para complementar respuestas
F10: Nivel de cumplimiento | I10: Observaciones
B11: REQUERIMIENTOS FUNCIONALES ORDENES Y PAGOS | F11: SI | G11: NO | H11: ADI
B13: 1 | C13: El sistema debe permitir registrar pedidos con fecha | H13: X
B14: 2 | C14: El sistema debe permitir registrar el cliente asociado a un pedido | H14: X
B15: 3 | C15: El sistema debe permitir registrar el estado del pedido | H15: X
B16: 4 | C16: El sistema debe calcular automáticamente el total del pedido (cantidad * precio por producto) | H16: X
B17: 6 | C17: El sistema debe mostrar el detalle de productos asociados a un pedido | H17: X
B18: 7 | C18: El sistema debe permitir agregar múltiples productos a un pedido, con cantidades variables | H18: X
B19: 9 | C19: El sistema debe gestionar devoluciones de pedidos según reglas del negocio | H19: X
B20: 10 | C20: El sistema debe gestionar cancelaciones de pedidos según reglas del negocio | H20: X
B21: 11 | C21: El sistema debe mostrar el tiempo estimado de entrega en el detalle del pedido | H21: X
B22: 12 | C22: El sistema debe permitir agregar productos al carrito desde la vista de detalle de producto | H22: X
B23: 14 | C23: El sistema debe mostrar el total acumulado del carrito
B24: 15 | C24: El sistema debe permitir modificar cantidades de productos en el carrito
B25: 16 | C25: El sistema debe permitir eliminar productos del carrito
B26: 17 | C26: El sistema debe aplicar automáticamente cupones activos en el carrito si cumplen condiciones
B27: 19 | C27: El sistema debe registrar el método de pago utilizado por el cliente en cada pedido
B28: 20 | C28: El sistema debe integrar pasarela de pago
B29: 21 | C29: El sistema debe registrar el uso de cupones en los pedidos
B30: 22 | C30: El sistema debe aplicar automáticamente cupones activos si cumplen condiciones | H30: X
B31: 23 | C31: El sistema debe mostrar el valor descontado al aplicar cupón | H31: X
B32: 24 | C32: El sistema debe mostrar mensaje de error si el cupón no es válido | H32: X
B33: 25 | C33: El sistema debe mostrar fecha de vencimiento del cupón | H33: X
B34: 26 | C34: El sistema debe permitir remover cupón aplicado | H34: X
B35: 27 | C35: El sistema debe calcular descuento correctamente en el total | H35: X
B36: 28 | C36: El sistema debe ocultar la sección de tienda al ir al checkout | H36: X
B37: 29 | C37: El sistema debe mostrar la sección de checkout | H37: X
B38: 30 | C38: El sistema debe ocultar el botón flotante del carrito | H38: X
B39: 31 | C39: El sistema debe hacer scroll al inicio de la página | H39: X
B40: 32 | C40: El sistema debe incluir botón "Volver al Carrito"
B41: 33 | C41: El sistema debe solicitar dirección completa de envío
B42: 34 | C42: El sistema debe solicitar ciudad
B43: 35 | C43: Ambos campos deben ser obligatorios
B44: 36 | C44: Los campos deben tener validación en tiempo real
B45: 37 | C45: El sistema debe ofrecer 3 métodos de pago: Tarjeta, PayPal, PSE
B46: 38 | C46: Los métodos deben mostrarse como radio buttons
B47: 39 | C47: Solo debe poder seleccionarse un método a la vez | H47: X
B48: 40 | C48: Tarjeta debe estar seleccionada por defecto | H48: X
B49: 41 | C49: El sistema debe mostrar campos de tarjeta condicionalmente | H49: X
B50: 42 | C50: El sistema debe solicitar: número de tarjeta, vencimiento, CVV | H50: X
B51: 43 | C51: El número de tarjeta debe tener formato de 16 dígitos | H51: X
B52: 44 | C52: El vencimiento debe tener formato MM/AA | H52: X
B53: 45 | C53: El CVV debe tener formato de 3 dígitos | H53: X
B54: 46 | C54: Todos los campos deben ser obligatorios | H54: X
B55: 47 | C55: El sistema debe mostrar lista de productos en el resumen | H55: X
B56: 48 | C56: Cada producto debe mostrar: imagen, nombre, precio x cantidad | H56: X
B57: 49 | C57: El sistema debe mostrar subtotal de productos
B58: 50 | C58: El sistema debe mostrar total final
B59: 51 | C59: El botón de pago debe mostrar el monto total
B60: 52 | C60: El sistema debe validar todos los campos antes de procesar
B61: 53 | C61: El botón debe mostrar loader durante el procesamiento | H61: X
B62: 54 | C62: El botón debe deshabilitarse durante el procesamiento | H62: X
B63: 55 | C63: El sistema debe simular procesamiento de pago (3 segundos) | H63: X
B64: 56 | C64: El sistema debe mostrar notificación de éxito tras pago exitoso | H64: X
B65: 57 | C65: El carrito debe vaciarse después de pago exitoso | H65: X
B66: 58 | C66: El sistema debe regresar a la vista de tienda | H66: X
B67: 59 | C67: El botón flotante debe reaparecer | H67: X

Sheet RF BANNER COOKIES
B2: LISTADO DE REQUERIMIENTOS DE SYNKRO | K2: ESTADISTICAS
K3: Requirimientos | L3: =COUNT(B12:D100) -> 8
B4: SI | C4: Marque con una equis (X) si el sistema cumple con la función descrita | K4: Cumplidos | L4: =COUNTIF(F12:F100,"X") -> 0
B5: NO | C5: Marque con una equis (X) si el sistema no cumple con la función descrita | K5: Porcentaje | L5: =_xludf.PERCENTOF(L4,L3) -> #NAME?
B6: ADI | C6: Marque con una equis (X) si el sistema debe adicionar la función descrita
B7: Observaciones: | D7: Espacio para complementar respuestas
F10: Nivel de cumplimiento | I10: Observaciones
B11: REQUERIMIENTOS FUNCIONALES BANNER COOKIES | F11: SI | G11: NO | H11: ADI
B13: 1 | C13: El sistema debe mostrar banner de cookies en la primera visita | G13: X
B14: 2 | C14: El banner debe posicionarse en la parte inferior de la pantalla | G14: X
B15: 3 | C15: El banner debe incluir texto explicativo sobre cookies | G15: X
B16: 4 | C16: El banner debe incluir enlace a "Política de Cookies" | G16: X
B17: 5 | C17: El banner debe incluir botón "Aceptar y Continuar" | G17: X
B18: 6 | C18: El sistema debe guardar la preferencia en localStorage | G18: X
B19: 7 | C19: El banner no debe mostrarse si ya fue aceptado | G19: X
B20: 8 | C20: El banner debe verificar preferencia en cada carga de página | G20: X

Sheet RF SOPORTE Y ASPECTOS LEGALES
B2: LISTADO DE REQUERIMIENTOS DE RDWATCH | K2: ESTADISTICAS
K3: Requirimientos | L3: =COUNT(B12:D100) -> 14
B4: SI | C4: Marque con una equis (X) si el sistema cumple con la función descrita | K4: Cumplidos | L4: =COUNTIF(F12:F100,"X") -> 0
B5: NO | C5: Marque con una equis (X) si el sistema no cumple con la función descrita | K5: Porcentaje | L5: =_xludf.PERCENTOF(L4,L3) -> #NAME?
B6: ADI | C6: Marque con una equis (X) si el sistema debe adicionar la función descrita
B7: Observaciones: | D7: Espacio para complementar respuestas
F10: Nivel de cumplimiento | I10: Observaciones
B11: REQUERIMIENTOS FUNCIONALES SOPORTE Y ASPECTOS LEGALES | F11: SI | G11: NO | H11: ADI
B13: 1 | C13: El sistema debe permitir redirigir a canales externos como WhatsApp o correo electrónico para soporte | H13: X
B14: 2 | C14: El sistema debe mostrar una sección de centro de ayuda (FAQs) | H14: X
B15: 3 | C15: El sistema debe permitir definir políticas legales como política de privacidad | H15: X
B16: 4 | C16: El sistema debe permitir definir políticas legales como términos y condiciones | H16: X
B17: 5 | C17: El sistema debe permitir registrar una política de envíos visible desde el footer del sitio | H17: X
B18: 6 | C18: El sistema debe permitir visualizar y clasificar las preguntas frecuentes (FAQs) por categorías | H18: X
B19: 7 | C19: El sistema debe permitir registrar una política de devoluciones visible desde el footer del sitio | H19: X
B20: 8 | C20: El sistema debe permitir mostrar información legal sobre el tratamiento de datos personales (cumplimiento de Habeas Data) | H20: X
B21: 9 | C21: El sistema debe mostrar una sección de "Aviso legal" con datos del responsable del sitio (empresa, NIT, dirección, contacto) | H21: X
B22: 10 | C22: El sistema debe permitir mostrar una ventana emergente (modal) para gestión de cookies con opción de aceptar o configurar | H22: X
B23: 11 | C23: El sistema debe permitir al cliente un soporte mediante un chatbot
B24: 12 | C24: El sistema debe permitir al usuario visualizar y aceptar la política de privacidad de la empresa
B25: 13 | C25: El sistema debe permitir al usuario visualizar y aceptar los términos y condiciones de la empresa
B26: 14 | C26: La factura electrónica debe contener elementos mínimos legales según el DIAN

Sheet Funcionales Carrito BE
B2: LISTADO DE REQUERIMIENTOS DE RDWATCH | K2: ESTADISTICAS
K3: Requirimientos | L3: =COUNT(B12:D100) -> 42
B4: SI | C4: =COUNTIF('No funcionales generales BE'!F12:F48,"x")+COUNTIF(#REF!,"x")+COUNTIF(#REF!,"x")+COUNTIF('RF PANEL USER'!F12:F30,"x")+COUNTIF(#REF!,"x")+COUNTIF(#REF!,"x")+COUNTIF(#REF!,"x")+COUNTIF(#REF!,"x")+COUNTIF('Funcionales PRODUCTOS E INVENTA'!F13:F22,"x")+COUNTIF(#REF!,"x")+COUNTIF('Funcionales Carrito BE'!F13:F21,"x")+_xleta.COUNTIF -> #REF! | K4: Cumplidos | L4: =COUNTIF(F12:F100,"X") -> 0
B5: NO | C5: Marque con una equis (X) si el sistema no cumple con la función descrita | K5: Porcentaje | L5: =_xludf.PERCENTOF(L4,L3) -> #NAME?
B6: ADI | C6: Marque con una equis (X) si el sistema debe adicionar la función descrita
B7: Observaciones: | D7: Espacio para complementar respuestas
F10: Nivel de cumplimiento | I10: Observaciones
B11: REQUERIMIENTOS FUNCIONALES CARRITO | F11: SI | G11: NO | H11: ADI
B13: 1 | C13: El sistema debe permitir agregar productos al carrito desde la vista de producto | G13: X
B14: 2 | C14: El sistema debe mostrar el total acumulado del carrito | G14: X
B15: 3 | C15: El sistema debe permitir modificar cantidades en el carrito | G15: X
B16: 4 | C16: El sistema debe permitir eliminar productos del carrito | G16: X
B17: 5 | C17: El sistema debe mostrar el carrito en la ezquina inferior derecha | G17: X
B18: 6 | C18: El sistema debe mostrar contador de productos en el icono de carrito | G18: X
B19: 7 | C19: El sistema debe mantener el estado del carrito si el usuario está logueado | G19: X
B20: 8 | C20: El sistema debe sincronizar el carrito entre todas las vistas | G20: X
B21: 9 | C21: El sistema debe mostrar imagen miniatura de productos en el carrito | G21: X
B22: 10 | C22: El sistema debe calcular automáticamente subtotales por producto | G22: X
B23: 11 | C23: El sistema debe permitir guardar carrito para compra posterior | G23: X
B24: 12 | C24: El sistema debe validar disponibilidad de stock antes de agregar al carrito | G24: X
... B54: 42 | C54: El sistema debe permitir ingresar código de cupón en el carrito | G54: X

Sheet RF CLIENTES Y USUARIOS
B2: LISTADO DE REQUERIMIENTOS DE RDWATCH | K2: ESTADISTICAS
K3: Requirimientos | L3: =COUNT(B12:D100) -> 27
B4: SI | C4: Marque con una equis (X) si el sistema cumple con la función descrita | K4: Cumplidos | L4: =COUNTIF(F12:F100,"X") -> 2
B5: NO | C5: Marque con una equis (X) si el sistema no cumple con la función descrita | K5: Porcentaje | L5: =_xludf.PERCENTOF(L4,L3) -> #NAME?
B6: ADI | C6: Marque con una equis (X) si el sistema debe adicionar la función descrita
B7: Observaciones: | D7: Espacio para complementar respuestas
F9: Nivel de cumplimiento | I9: Observaciones
B10: RF GESTIÓN DE CLIENTES Y USUARIOS | F10: SI | G10: NO | H10: ADI
B12: 1 | C12: El sistema debe permitir registrar información de clientes | F12: X
B13: 2 | C13: El sistema debe permitir editar información de los clientes
B14: 3 | C14: El sistema debe permitir visualizar información de clientes | F14: X
B15: 4 | C15: El sistema debe mostrar el historial de compras del cliente en su perfil
B16: 5 | C16: El sistema debe permitir registrar clientes con campos obligatorios
B17: 6 | C17: El sistema debe validar que el número de identificación del cliente sea único
B18: 7 | C18: El sistema debe permitir asociar múltiples direcciones a un mismo cliente
B19: 8 | C19: El sistema debe enviar notificaciones automáticas al cliente sobre el estado del pedido
B20: 9 | C20: El sistema debe registrar un historial de actividad por usuario
B21: 10 | C21: El sistema debe mostrar al cliente su información básica (nombre, email, teléfono)
B22: 11 | C22: El sistema debe permitir al cliente gestionar sus direcciones (crear, editar, eliminar)
B23: 12 | C23: El sistema debe permitir registrar usuarios administrativos con credenciales únicas
B24: 13 | C24: El sistema debe restringir el acceso a módulos según el rol del usuario
B25: 14 | C25: El sistema debe registrar intentos fallidos de autenticación de usuario
B26: 15 | C26: El sistema debe permitir recuperación de contraseña mediante correo electrónico seguro
... B38: 27 | C38: El sistema debe permitir a los clientes realizar seguimiento en tiempo real del estado de sus pedidos

Sheet R COLORES
B2: LISTADO DE REQUERIMIENTOS DE RDWATCH | K2: ESTADISTICAS
K3: Requirimientos | L3: =COUNT(B12:D180) -> 169
B4: SI | C4: Marque con una equis (X) si el sistema cumple con la función descrita | K4: Cumplidos | L4: =COUNTIF(F12:F180,"X") -> 169
B5: NO | C5: Marque con una equis (X) si el sistema no cumple con la función descrita
B6: ADI | C6: Marque con una equis (X) si el sistema debe adicionar la función descrita | K6: Porcentaje | L6: =L3/L4 -> 1
B7: Observaciones: | D7: Espacio para complementar respuestas
F9: Nivel de cumplimiento | I9: OBSERVACIONES
B10: Requerimientos de Paleta de Colores y Sistema Cromático | F10: SI | G10: NO | H10: ADI
B12: 1 | C12: El sistema debe definir el color oro principal como #b8860b (DarkGoldenrod | F12: x
B13: 2 | C13: El color oro principal debe usarse en botones de acción primarios | F13: x
B14: 3 | C14: El color oro principal debe usarse en íconos destacados de servicios | F14: x
B15: 4 | C15: El color oro principal debe usarse en enlaces activos y elementos interactivos | F15: x
B16: 5 | C16: El color oro principal debe usarse en badges y etiquetas premium | F16: x
B17: 6 | C17: El color oro principal debe transmitir sensación de lujo y exclusividad | F17: x
B18: 7 | C18: El color oro principal debe tener contraste mínimo 4.5:1 sobre fondo blanco | F18: x
B19: 8 | C19: El sistema debe definir el color oro oscuro como #996515 | F19: x
B20: 9 | C20: El color oro oscuro debe usarse en estados hover de botones primarios | F20: x
B21: 10 | C21: El color oro oscuro debe usarse en títulos importantes y encabezados | F21: x
B22: 11 | C22: El color oro oscuro debe usarse en bordes de elementos destacados | F22: x
B23: 12 | C23: El color oro oscuro debe proporcionar mayor contraste que el oro principal | F23: x
... B180: 169 | C180: Los colores de error deben ser siempre los mismos en todo el sistema | F180: x
